pyjwt_wrapper/__init__.py
pyjwt_wrapper/authentication.py
pyjwt_wrapper/authorization.py
pyjwt_wrapper-0.6.0.dist-info/METADATA
pyjwt_wrapper-0.6.0.dist-info/WHEEL
pyjwt_wrapper-0.6.0.dist-info/top_level.txt
pyjwt_wrapper-0.6.0.dist-info/RECORD
