Metadata-Version: 2.1
Name: pyjwt-wrapper
Version: 0.6.0
Summary: An easy to use wrapper around PyJWT for authentication and authorization.
Home-page: https://github.com/nicc777/pyjwt-wrapper
Author: Nico Coetzee
Author-email: nicc777@gmail.com
License: UNKNOWN
Project-URL: Bug Reports, https://github.com/nicc777/pyjwt-wrapper/issues
Project-URL: Source, https://github.com/nicc777/pyjwt-wrapper
Keywords: jwt,pyjwt,library
Platform: UNKNOWN
Classifier: Development Status :: 4 - Beta
Classifier: Intended Audience :: Developers
Classifier: Topic :: Software Development :: Libraries
Classifier: License :: OSI Approved :: MIT License
Classifier: Programming Language :: Python :: 3
Classifier: Programming Language :: Python :: 3.7
Classifier: Programming Language :: Python :: 3.8
Classifier: Programming Language :: Python :: 3 :: Only
Requires-Python: >=3.7, <4
Requires-Dist: pyjwt
Provides-Extra: dev
Requires-Dist: check-manifest ; extra == 'dev'
Provides-Extra: test
Requires-Dist: coverage ; extra == 'test'
